firewalla_api_ctek/__init__.py
firewalla_api_ctek/boxdevices.py
firewalla_api_ctek/boxes.py
firewalla_api_ctek-0.0.21.dist-info/LICENSE
firewalla_api_ctek-0.0.21.dist-info/METADATA
firewalla_api_ctek-0.0.21.dist-info/WHEEL
firewalla_api_ctek-0.0.21.dist-info/top_level.txt
firewalla_api_ctek-0.0.21.dist-info/RECORD
